README.md
setup.py
qazse/__init__.py
qazse/db.py
qazse/file.py
qazse/log.py
qazse/requser.py
qazse/seo.py
qazse/spiders.py
qazse/sys.py
qazse/text.py
qazse/time.py
qazse/upload.py
qazse.egg-info/PKG-INFO
qazse.egg-info/SOURCES.txt
qazse.egg-info/dependency_links.txt
qazse.egg-info/requires.txt
qazse.egg-info/top_level.txt