Metadata-Version: 1.0
Name: qazse
Version: 0.6.9
Summary: 自己用的工具包
Home-page: http://w.qiiing.com
Author: QazseWong
Author-email: w@qiiing.com
License: MIT Licence
Keywords: pip,qazse,QazseWong
Platform: any
